{
  "siteName": "Roots & Gums",
  "siteDescription": "Advanced dental care with a personal touch",
  "logo": "/images/logo.png",
  "navigation": {
    "links": [
      { "name": "Home", "href": "/" },
      { "name": "About", "href": "/about" },
      { "name": "Services", "href": "/services" },
      { "name": "Testimonials", "href": "/testimonials" },
      { "name": "Contact", "href": "/contact" }
    ],
    "cta": {
      "text": "Book Appointment",
      "href": "/book-appointment"
    }
  },
  "hero": {
    "welcomeText": "Welcome to Roots & Gums",
    "title": "Advanced Dental Care",
    "subtitle": "For Your Family",
    "description": "Experience state-of-the-art dentistry in a warm and caring environment. Our expert dentists are committed to providing you with the highest quality dental care.",
    "image": "/images/rootsBg.jpg",
    "imageAlt": "Modern dental care at Roots & Gums",
    "cta": {
      "primary": {
        "text": "Book Appointment",
        "link": "/book-appointment"
      },
      "secondary": {
        "text": "Our Services",
        "link": "/services"
      }
    }
  },
  "contact": {
    "phone": "+917304809511",
    "email": "info@rootsandgums.com",
    "address": "Abu Asad Premises, Military Rd, Sankasth Pada Welfare Society, Marol, Andheri East, Mumbai, Maharashtra 400059",
    "socialLinks": {
      "facebook": "/",
      "instagram": "/",
      "twitter": "/"
    },
    "whatsapp": "+917304809511",
    "googleMapsUrl": "https://www.google.com/maps/embed/v1/place?q=Roots+and+Gums+Dental+Studio&key=AIzaSyBFw0Qbyq9zTFTd-tUY6dZWTgaQzuU17R8",
    "googleFormsUrl": "https://forms.gle/qqtgVA3UsT95RvaSA",
    "section": {
      "title": "Connect with Us",
      "description": "Have questions? Our friendly team is here to help you achieve optimal dental health.",
      "whatsappMessage": "Hello! I'd like to schedule an appointment at Roots & Gums.",
      "whatsappButtonText": "Message Us",
      "bookAppointmentText": "Schedule Visit"
    },
    "hours": "10:00 AM - 1:00 PM & 4:00 PM - 9:30 PM (Closed on Sunday)"
  },
  "theme": {
    "name": "modern",
    "colorScheme": "teal",
    "fonts": {
      "heading": "Playfair Display",
      "body": "Inter"
    },
    "colors": {
      "primary": {
        "50": "#f0fdfa",
        "500": "#14b8a6",
        "700": "#0f766e"
      },
      "secondary": {
        "50": "#f8fafc",
        "500": "#64748b",
        "700": "#334155"
      }
    }
  },
  "services": {
    "title": "Our Services",
    "description": "Comprehensive dental care using the latest technology and techniques",
    "items": [
      {
        "id": "general-dentistry",
        "title": "General Dentistry",
        "description": "Complete family dental care with a focus on prevention",
        "icon": "tooth",
        "features": [
          "Dental Check-ups",
          "Professional Cleaning",
          "Cavity Treatment",
          "Preventive Care"
        ],
        "image": "/images/general_dentistry.jpg"
      },
      {
        "id": "cosmetic-dentistry",
        "title": "Cosmetic Dentistry",
        "description": "Advanced treatments to enhance your smile",
        "icon": "sparkles",
        "features": [
          "Teeth Whitening",
          "Porcelain Veneers",
          "Dental Crowns",
          "Smile Design"
        ],
        "image": "/images/cosmetic_dentistry.jpg"
      },
      {
        "id": "orthodontics",
        "title": "Orthodontics",
        "description": "Modern solutions for teeth alignment",
        "icon": "adjustments",
        "features": [
          "Clear Aligners",
          "Traditional Braces",
          "Invisalign",
          "Retainers"
        ],
        "image": "/images/orthodontics.webp"
      }
    ],
    "icons": {
      "tooth": {
        "path": "M4.5 12.5l3-3m0 0l3 3m-3-3v7m6-7l3-3m0 0l3 3m-3-3v7"
      },
      "sparkles": {
        "path": "M5 3v4M3 5h4M6 17v4m-2-2h4m5-16l2.286 6.857L21 12l-5.714 2.143L13 21l-2.286-6.857L5 12l5.714-2.143L13 3z"
      },
      "adjustments": {
        "path": "M12 6V4m0 2a2 2 0 100 4m0-4a2 2 0 110 4m-6 8a2 2 0 100-4m0 4a2 2 0 110-4m0 4v2m0-6V4m6 6v10m6-2a2 2 0 100-4m0 4a2 2 0 110-4m0 4v2m0-6V4"
      }
    }
  },
  "testimonials": [
    {
      "id": 1,
      "name": "Naser",
      "rating": 5,
      "comment": "I had a fantastic experience at Roots and Gums Dental Clinic! The staff was incredibly friendly and professional from the moment I walked in. Dr was thorough in explaining my treatment options and made me feel comfortable throughout the process. The clinic itself is modern, clean, and welcoming, which put me at ease. I especially appreciated how gentle and attentive the team was during my procedure, making sure I was comfortable at every step. I highly recommend Roots and Gums for anyone looking for top-notch dental care!",
      "image": "/images/testimonials/Naser.png"
    },
    {
      "id": 2,
      "name": "Diksha",
      "rating": 5,
      "comment": "Great experience at Roots and Gums 🦷 Dr. Pradeep Bafna and the whole team were professional, kind, and made me feel super comfortable. Highly recommend for quality dental care! 😊",
      "image": "/images/testimonials/Diksha.png"
    },
    {
      "id": 3,
      "name": "Vishakha",
      "rating": 5,
      "comment": "A very hygienic clinic with all facilities. I would recommend Dr. Pradeep & Dr. Sonali for their professionalism, quality of care & outstanding premises.Thumbs up for the good work!💯👍🤗",
      "image": "/images/testimonials/Vishakha.png"
    },
    {
      "id": 4,
      "name": "Leona",
      "rating": 5,
      "comment": "I had a root canal and capping done for my teeth at Roots and Gums Dental Studio, and the treatment was really good. The dental care was careful and thorough. The service was excellent and the dentists were skilled. Making appointments was easy, and the overall way they handled things at the clinic was great.",
      "image": "/images/testimonials/Leona.png"
    }
  ],
  "about": {
    "section_title": "About Our Doctors",
    "title": "Meet Our Doctors",
    "description": "They are committed to providing you with the highest quality care in a comfortable environment.",
    "clinicOverview": {
      "title": "Modern Facilities",
      "description": "Experience dental care in our state-of-the-art facility equipped with the latest technology for your comfort and the best possible treatment outcomes.",
      "image": "/images/dental_interior.jpg",
      "imageAlt": "Modern dental clinic interior"
    },
    "values": [
      {
        "title": "Patient-Centric Care",
        "description": "Your comfort and satisfaction are our top priorities."
      },
      {
        "title": "Latest Technology",
        "description": "We utilize advanced dental technology for precise and comfortable treatments."
      },
      {
        "title": "Gentle Approach",
        "description": "Our gentle and caring approach ensures a stress-free dental experience."
      }
    ]
  },
  "team": [
    {
      "id": 1,
      "name": "Dr. Viren",
      "role": "Lead Dentist",
      "specialization": "Cosmetic Dentistry",
      "bio": "Dr. Viren has over 15 years of experience in cosmetic dentistry and is committed to providing the highest quality dental care.",
      "image": "/images/Male_doctor_placeholder.jpg"
    },
    {
      "id": 2,
      "name": "Dr. Pradeep",
      "role": "Lead Dentist",
      "specialization": "Cosmetic Dentistry",
      "bio": "Dr. Pradeep has over 15 years of experience in cosmetic dentistry and is committed to providing the highest quality dental care.",
      "image": "/images/Male_doctor_placeholder.jpg"
    },
    {
      "id": 3,
      "name": "Dr. Sonali",
      "role": "Lead Dentist",
      "specialization": "Cosmetic Dentistry",
      "bio": "Dr. Sonali has over 15 years of experience in cosmetic dentistry and is committed to providing the highest quality dental care.",
      "image": "/images/Doctor_placeholder.jpg"
    }
  ],
  "bookAppointment": {
    "title": "Book Your Appointment",
    "description": "Schedule your visit with our dental experts. We'll get back to you within 24 hours to confirm your appointment."
  }
}
